k2Vault/__init__.py
k2vault-0.1.0.dist-info/METADATA
k2vault-0.1.0.dist-info/WHEEL
k2vault-0.1.0.dist-info/top_level.txt
k2vault-0.1.0.dist-info/RECORD
