Metadata-Version: 2.1
Name: k2vault
Version: 0.1.0
Summary: A reusable Python module to utilize Azure KeyVaults
Home-page: https://github.com/k2digidata/k2Vault
Author-email: h.davoodi@k2-systems.de
Classifier: Programming Language :: Python :: 3
Classifier: License :: OSI Approved :: MIT License
Classifier: Operating System :: OS Independent
Requires-Python: >=3.7
